ros_rosidl_core_generators-0.3.1.data/data/share/ament_index/resource_index/package_run_dependencies/rosidl_core_generators
ros_rosidl_core_generators-0.3.1.data/data/share/ament_index/resource_index/packages/rosidl_core_generators
ros_rosidl_core_generators-0.3.1.data/data/share/ament_index/resource_index/parent_prefix_path/rosidl_core_generators
ros_rosidl_core_generators-0.3.1.data/data/share/rosidl_core_generators/local_setup.bash
ros_rosidl_core_generators-0.3.1.data/data/share/rosidl_core_generators/local_setup.dsv
ros_rosidl_core_generators-0.3.1.data/data/share/rosidl_core_generators/local_setup.sh
ros_rosidl_core_generators-0.3.1.data/data/share/rosidl_core_generators/local_setup.zsh
ros_rosidl_core_generators-0.3.1.data/data/share/rosidl_core_generators/package.dsv
ros_rosidl_core_generators-0.3.1.data/data/share/rosidl_core_generators/package.xml
ros_rosidl_core_generators-0.3.1.data/data/share/rosidl_core_generators/cmake/ament_cmake_export_dependencies-extras.cmake
ros_rosidl_core_generators-0.3.1.data/data/share/rosidl_core_generators/cmake/rosidl_core_generators-extras.cmake
ros_rosidl_core_generators-0.3.1.data/data/share/rosidl_core_generators/cmake/rosidl_core_generatorsConfig-version.cmake
ros_rosidl_core_generators-0.3.1.data/data/share/rosidl_core_generators/cmake/rosidl_core_generatorsConfig.cmake
ros_rosidl_core_generators-0.3.1.data/data/share/rosidl_core_generators/environment/ament_prefix_path.dsv
ros_rosidl_core_generators-0.3.1.data/data/share/rosidl_core_generators/environment/ament_prefix_path.sh
ros_rosidl_core_generators-0.3.1.data/data/share/rosidl_core_generators/environment/path.dsv
ros_rosidl_core_generators-0.3.1.data/data/share/rosidl_core_generators/environment/path.sh
rosidl_core_generators/_dummy.cpython-310-x86_64-linux-gnu.so
ros_rosidl_core_generators-0.3.1.dist-info/METADATA
ros_rosidl_core_generators-0.3.1.dist-info/WHEEL
ros_rosidl_core_generators-0.3.1.dist-info/top_level.txt
ros_rosidl_core_generators-0.3.1.dist-info/RECORD
