Metadata-Version: 2.4
Name: ros-rosidl-core-generators
Version: 0.3.1
Summary: A ROS package providing CMake functionality to manage buildtime and runtime dependencies for ROS interface packages, simplifying their creation.
Dynamic: description
Dynamic: description-content-type
Dynamic: summary
